setup.py
file_lib/__init__.py
file_lib/csv_file.py
file_lib/dict_utils.py
file_lib/file_utils.py
file_lib/gzip_utils.py
file_lib/json_utils.py
file_lib/string_utils.py
file_lib/zip_utils.py
file_lib.egg-info/PKG-INFO
file_lib.egg-info/SOURCES.txt
file_lib.egg-info/dependency_links.txt
file_lib.egg-info/requires.txt
file_lib.egg-info/top_level.txt