Metadata-Version: 1.1
Name: file-lib
Version: 1.0.2
Summary: File Library
Home-page: https://github.com/Akira-Taniguchi/file_lib
Author: AkiraTaniguchi
Author-email: dededededaiou2003@yahoo.co.jp
License: MIT
Keywords: csv reaader writer unicode kanji gz zip compress unzip json directory file backup
Platform: UNKNOWN
Classifier: Development Status :: 5 - Production/Stable
Classifier: Programming Language :: Python :: 2.7
Classifier: Intended Audience :: Developers
Classifier: License :: OSI Approved :: MIT License
